{
  "citationitems": [
    {
      "first-reference-note-number": 1,
      "id": "statute-7",
      "label": "page",
      "locator": ", sec. 25 & 143",
      "near-note": false,
      "position": 1
    }
  ],
  "items": [
    {
      "container-title": "Pennsylvania Statutes Annotated",
      "id": "statute-7",
      "issued": {
        "raw": "2010"
      },
      "jurisdiction": "us;pa",
      "number": "tit. 53",
      "publication-date": {
        "raw": "2010"
      },
      "publisher": "West",
      "section": "sec. 342",
      "title": "Parking Authority Law",
      "type": "legislation",
      "volume": "53"
    }
  ],
  "result": "<i>Parking Authority Law</i>, <i>supra</i> note 1 tit 53, sect\u00a0342, 25 &#38; 143.",
  "stylename": "mlz-mcgill-fr-v7"
}