{
  "citationitems": [
    {
      "first-reference-note-number": 1,
      "id": "video-1",
      "label": null,
      "locator": 125,
      "near-note": false,
      "position": 1
    }
  ],
  "items": [
    {
      "URL": "http://www.youtube.com/watch?v=LI3Id1FMaqs",
      "accessed": {
        "raw": "2012-05-02"
      },
      "id": "video-1",
      "issued": {
        "raw": "1998"
      },
      "medium": "Videotape",
      "publisher": "Federal Judicial Center",
      "title": "Orientation Seminar for Federal Judicial Law Clerks",
      "type": "video",
      "volume": "Part 1"
    }
  ],
  "result": "\u201cOrientation Seminar for Federal Judicial Law Clerks,\u201d 125.",
  "stylename": "mlz-cms-full"
}